heimdall/__init__.py
heimdall/lib/pickles/__init__.py
heimdall/lib/pickles/logger.py
heimdall/lib/pickles/pickles.py
heimdall/lib/pickles/tests/__init__.py
heimdall/lib/pickles/tests/test_pickles.py
heimdall/lib/singleton/__init__.py
heimdall/lib/singleton/singleton.py
heimdall/lib/singleton/tests/__init__.py
heimdall/lib/singleton/tests/test_singleton.py
heimdall_utils-0.1.2.dist-info/METADATA
heimdall_utils-0.1.2.dist-info/WHEEL
heimdall_utils-0.1.2.dist-info/RECORD
