Metadata-Version: 2.1
Name: heimdall-utils
Version: 0.1.2
Summary: 
Author: joaocarlos-hotmart
Author-email: joao.almeida@hotmart.com
Requires-Python: >=3.8,<4.0
Classifier: Programming Language :: Python :: 3
Classifier: Programming Language :: Python :: 3.8
Classifier: Programming Language :: Python :: 3.9
Classifier: Programming Language :: Python :: 3.10
Classifier: Programming Language :: Python :: 3.11
Classifier: Programming Language :: Python :: 3.12
